mvgkde/__init__.py
mvgkde/_core.py
mvgkde/_version.py
mvgkde/_version.pyi
mvgkde/py.typed
mvgkde-0.2.0.dist-info/METADATA
mvgkde-0.2.0.dist-info/WHEEL
mvgkde-0.2.0.dist-info/licenses/LICENSE
mvgkde-0.2.0.dist-info/licenses/NOTICE
mvgkde-0.2.0.dist-info/RECORD
