Metadata-Version: 2.3
Name: mvgkde
Version: 0.2.0
Summary: MultiVariate Gaussian Kernel Density Estimator
Project-URL: Homepage, https://github.com/nstarman/mvgkde
Project-URL: Bug Tracker, https://github.com/nstarman/mvgkde/issues
Project-URL: Changelog, https://github.com/nstarman/mvgkde/releases
Author-email: Nathaniel Starkman <nstarman@users.noreply.github.com>
License: 
Classifier: Development Status :: 3 - Alpha
Classifier: Intended Audience :: Developers
Classifier: Intended Audience :: Science/Research
Classifier: License :: OSI Approved :: Apache Software License
Classifier: Operating System :: OS Independent
Classifier: Programming Language :: Python
Classifier: Programming Language :: Python :: 3
Classifier: Programming Language :: Python :: 3 :: Only
Classifier: Programming Language :: Python :: 3.11
Classifier: Programming Language :: Python :: 3.12
Classifier: Programming Language :: Python :: 3.13
Classifier: Topic :: Scientific/Engineering
Classifier: Typing :: Typed
Requires-Python: >=3.11
Requires-Dist: jax>=0.4.35
Requires-Dist: jaxlib>=0.4.35
Requires-Dist: jaxtyping>=0.2.34
Requires-Dist: numpy>=2.1.2
Provides-Extra: dev
Requires-Dist: hypothesis>=6.115.4; extra == 'dev'
Requires-Dist: pytest-cov>=3; extra == 'dev'
Requires-Dist: pytest>=6; extra == 'dev'
Provides-Extra: test
Requires-Dist: hypothesis>=6.115.4; extra == 'test'
Requires-Dist: pytest-cov>=3; extra == 'test'
Requires-Dist: pytest>=6; extra == 'test'
